webhook_router/__init__.py
webhook_router/app.py
webhook_router/utils.py
webhook_router/views.py
webhook_router/services/__init__.py
webhook_router/services/database.py
webhook_router/services/message.py
webhook_router-0.1a2.dist-info/DESCRIPTION.rst
webhook_router-0.1a2.dist-info/METADATA
webhook_router-0.1a2.dist-info/RECORD
webhook_router-0.1a2.dist-info/WHEEL
webhook_router-0.1a2.dist-info/entry_points.txt
webhook_router-0.1a2.dist-info/metadata.json
webhook_router-0.1a2.dist-info/top_level.txt
