Metadata-Version: 2.0
Name: webhook-router
Version: 0.1a2
Summary: Test project for listening to webhooks and routing to websockets.
Home-page: https://github.com/hjalves/webhook-router
Author: Humberto Alves
Author-email: hjalves@live.com
License: MIT
Keywords: webhook,websocket
Platform: UNKNOWN
Classifier: Development Status :: 2 - Pre-Alpha
Classifier: Environment :: Console
Classifier: Intended Audience :: Developers
Classifier: Operating System :: POSIX :: Linux
Classifier: Programming Language :: Python :: 3
Classifier: Programming Language :: Python :: 3.6
Requires-Dist: aiohttp
Requires-Dist: aiohttp-cors
Requires-Dist: aiohttp-remotes
Requires-Dist: colorlog
Requires-Dist: toml
